README.md
setup.py
gic2api/__init__.py
gic2api/inpaas/__init__.py
gic2api/inpaas/test_gic2_lvs.py
openapi/__init__.py
openapi/com.py
openapi/inpaas/__init__.py
openapi/inpaas/test_haproxy.py
pytestOGSMplugin/__init__.py
pytestOGSMplugin/pytest_ogsm.py
pytestOGSMplugin/templates/__init__.py
pytestOGSMplugin/templates/templates.html
pytest_ogsm_plugin.egg-info/PKG-INFO
pytest_ogsm_plugin.egg-info/SOURCES.txt
pytest_ogsm_plugin.egg-info/dependency_links.txt
pytest_ogsm_plugin.egg-info/entry_points.txt
pytest_ogsm_plugin.egg-info/requires.txt
pytest_ogsm_plugin.egg-info/top_level.txt
tests/__init__.py
tests/conftest.py