Metadata-Version: 2.1
Name: pytest-ogsm-plugin
Version: 3.4.5
Summary: 针对特定项目定制化插件，优化了pytest报告展示方式,并添加了项目所需特定参数
Home-page: https://github.com/cw010/pytest_ogsm_plugin
Author: cw
Author-email: cwalk.t@gmail.com
License: proprietary
Keywords: pytest,py.test,pytest_ogsm_plugin
Platform: UNKNOWN
Classifier: Framework :: Pytest
Classifier: Programming Language :: Python :: 3.9
